Workbook

Sheet 1_Master_Dashboard
A1: ⬇️ PARAMETER (HIER EINTRAGEN) ⬇️ | B1: ✏️ EINGABE | D1: 🔒 FINANZEN (AUTOMATISCH) 🔒 | E1: 🔒 FORMEL
A2: Basispreis pro g (CHF) | B2: 35 | D2: Wirtschaftlicher Gesamterlös (CHF) | E2: =SUM('3a_Log_Morris'!L:L) + SUM('3b_Log_Boryana'!L:L)
A3: Startmenge Schale (g) | B3: 100 | D3: Total Spesen abgezogen (CHF) | E3: =SUM('3a_Log_Morris'!I:I) + SUM('3b_Log_Boryana'!I:I)
A4: Warn-Schwelle Restbestand (g) | B4: 20 | D4: Echter Netto-Erlös (CHF) | E4: =E2-E3
A5: Mein Investment Start (CHF) | B5: 500
A6: Fremdschuld Start (CHF) | B6: 3000 | D6: 🔒 AUSZAHLUNGS-WASSERFALL 🔒 | E6: 🔒 FORMEL
A7: Gewinnanteil Morris (%) | B7: 0.5 | D7: 1. Rückzahlung an Morris (CHF) | E7: =MIN(B5, E4)
A8: Gewinnanteil Boryana (%) | B8: 0.5 | D8: 2. Basisanteil -> Fremdschuld (CHF) | E8: =MIN(B6, E4-E7, B13*B2)
D9: 3. Total Gewinn (Verteilbar) (CHF) | E9: =MAX(0, E4-E7-E8)
A10: 🔒 MENGEN & LAGER (AUTOMATISCH) 🔒 | B10: 🔒 FORMEL | D10: -> Profit Morris (CHF) | E10: =E9*B7
A11: Verkaufte Menge (extern) (g) | B11: =SUMIF('3a_Log_Morris'!C:C, "Verkauf", '3a_Log_Morris'!F:F) + SUMIF('3b_Log_Boryana'!C:C, "Verkauf", '3b_Log_Boryana'!F:F) | D11: -> Profit Boryana (CHF) | E11: =E9*B8
A12: Eigene Entnahmen (intern) (g) | B12: =SUMIF('3a_Log_Morris'!C:C, "Eigenkonsum", '3a_Log_Morris'!F:F) + SUMIF('3b_Log_Boryana'!C:C, "Eigenkonsum", '3b_Log_Boryana'!F:F)
A13: Gesamtmenge raus (g) | B13: =B11+B12 | D13: 🔒 OFFENE SCHULDEN & STATUS 🔒 | E13: 🔒 FORMEL
A14: Restbestand Schale (g) | B14: =B3-B13 | D14: Mein Investment noch offen (CHF) | E14: =B5-E7
A15: Lagerwert Basis (CHF) | B15: =B14*B2 | D15: Fremdschuld noch offen (CHF) | E15: =B6-E8
A16: Lager-Warnung Status | B16: =IF(B14<B4, "⚠️ LAGER KNAPP", "✅ OK") | D16: Offene Kunden-Rechnungen (CHF) | E16: =SUMIF('3a_Log_Morris'!E:E, "Offen", '3a_Log_Morris'!G:G) + SUMIF('3b_Log_Boryana'!E:E, "Offen", '3b_Log_Boryana'!G:G)
D17: Unbezahlte Eigenschulden Morris (CHF) | E17: ='2_Investoren_Schulden'!G8
A18: 🔒 KASSENSTURZ (AUTOMATISCH) 🔒 | B18: 🔒 FORMEL | D18: Unbezahlte Eigenschulden Boryana (CHF) | E18: ='2_Investoren_Schulden'!G9
A19: Erwarteter Cash-Bestand (Bar) (CHF) | B19: =SUMIFS('3a_Log_Morris'!G:G, '3a_Log_Morris'!E:E, "Bezahlt", '3a_Log_Morris'!H:H, "Bar") + SUMIFS('3b_Log_Boryana'!G:G, '3b_Log_Boryana'!E:E, "Bezahlt", '3b_Log_Boryana'!H:H, "Bar") | D19: Break-Even Status | E19: =IF(E14<=0, "VOLL IM PROFIT 🚀", "IN TILGUNG ⏳")
A20: Erwarteter Twint/Bank-Bestand (CHF) | B20: =SUMIFS('3a_Log_Morris'!G:G, '3a_Log_Morris'!E:E, "Bezahlt", '3a_Log_Morris'!H:H, "Twint") + SUMIFS('3b_Log_Boryana'!G:G, '3b_Log_Boryana'!E:E, "Bezahlt", '3b_Log_Boryana'!H:H, "Twint") | D20: Ø Netto-Marge gesamt (%) | E20: =IF(E2>0, E9/E2, 0)
A21: Gesamt Liquidität physisch (CHF) | B21: =B19+B20

Sheet 2_Investoren_Schulden
A1: Kategorie | B1: Name | C1: 🔒 Start/Total (CHF) | D1: ✏️ Bereits Bezahlt (CHF) | E1: ✏️ Manuelle Zusatz-Zahlung (CHF) | F1: 🔒 Offener Saldo (CHF) | G1: 🔒 Status
A2: INVESTOR | B2: Morris | C2: ='1_Master_Dashboard'!B5 | D2: ='1_Master_Dashboard'!E7 | E2: 0 | F2: =C2-D2-E2 | G2: =IF(F2<=0, "Abbezahlt ✅", "Offen ⏳")
A3: INVESTOR | B3: Dritte Person 1 | C3: ='1_Master_Dashboard'!B6 | D3: ='1_Master_Dashboard'!E8 | E3: 0 | F3: =C3-D3-E3 | G3: =IF(F3<=0, "Abbezahlt ✅", "Offen ⏳")
A4: INVESTOR | B4: Dritte Person 2 | C4: 0 | D4: 0 | E4: 0 | F4: =C4-D4-E4
A7: INTERNE KÄUFER | B7: Morris (Eigenkonsum) | C7: ='1_Master_Dashboard'!B2*SUMIF('3a_Log_Morris'!C:C, "Eigenkonsum", '3a_Log_Morris'!F:F) | D7: 0 | E7: 0 | F7: =C7-D7-E7 | G7: =IF(F7>0, "Schulden in Kasse legen 🔴", "Sauber 🟢")
A8: INTERNE KÄUFER | B8: Boryana (Eigenkonsum) | C8: ='1_Master_Dashboard'!B2*SUMIF('3b_Log_Boryana'!C:C, "Eigenkonsum", '3b_Log_Boryana'!F:F) | D8: 0 | E8: 0 | F8: =C8-D8-E8 | G8: =IF(F8>0, "Schulden in Kasse legen 🔴", "Sauber 🟢")
A9: INTERNE KÄUFER

Sheet 3a_Log_Morris
B1: ⬇️ HIER EINTRAGEN (EINGABEBEREICH) ⬇️ | K1: 🚫 NICHT ÄNDERN (AUTOMATISCHE FORMELN) 🚫
A4: 🔒 Nr | B4: ✏️ Datum | C4: ✏️ Art | D4: ✏️ Kunde / Notiz | E4: ✏️ Zahlung | F4: ✏️ Menge (g) | G4: ✏️ Preis (CHF) | H4: ✏️ Zahlungsart | I4: ✏️ Spesen (CHF) | J4: ✏️ Spesen-Kategorie | K4: 🔒 Basiswert (CHF) | L4: 🔒 Erlös intern (CHF) | M4: 🔒 Netto Profit (CHF) | N4: 🔒 Deal-Rating | O4: 🔒 Lager-Warnung
A5: 1 | E5: Offen | F5: 0 | G5: 0 | H5: Bar | I5: 0 | J5: Fahrtkosten | K5: =F5*'1_Master_Dashboard'!B$2 | L5: =IF(C5="Verkauf", G5, K5) | M5: =L5-K5-I5 | N5: =IF(F5>0, IF((G5/F5)>('1_Master_Dashboard'!B$2*1.2), "Top Deal 🚀", IF((G5/F5)<'1_Master_Dashboard'!B$2, "Verlust ⚠️", "Standard")), "") | O5: =IF('1_Master_Dashboard'!B$14<0, "MINUS BESTAND ❌", "OK")
A6: 2 | E6: Offen | F6: 0 | G6: 0 | H6: Bar | I6: 0 | J6: Fahrtkosten | K6: =F6*'1_Master_Dashboard'!B$2 | L6: =IF(C6="Verkauf", G6, K6) | M6: =L6-K6-I6 | N6: =IF(F6>0, IF((G6/F6)>('1_Master_Dashboard'!B$2*1.2), "Top Deal 🚀", IF((G6/F6)<'1_Master_Dashboard'!B$2, "Verlust ⚠️", "Standard")), "") | O6: =IF('1_Master_Dashboard'!B$14<0, "MINUS BESTAND ❌", "OK")
A7: 3 | E7: Offen | F7: 0 | G7: 0 | H7: Bar | I7: 0 | J7: Fahrtkosten | K7: =F7*'1_Master_Dashboard'!B$2 | L7: =IF(C7="Verkauf", G7, K7) | M7: =L7-K7-I7 | N7: =IF(F7>0, IF((G7/F7)>('1_Master_Dashboard'!B$2*1.2), "Top Deal 🚀", IF((G7/F7)<'1_Master_Dashboard'!B$2, "Verlust ⚠️", "Standard")), "") | O7: =IF('1_Master_Dashboard'!B$14<0, "MINUS BESTAND ❌", "OK")
A8: 4 | E8: Offen | F8: 0 | G8: 0 | H8: Bar | I8: 0 | J8: Fahrtkosten | K8: =F8*'1_Master_Dashboard'!B$2 | L8: =IF(C8="Verkauf", G8, K8) | M8: =L8-K8-I8 | N8: =IF(F8>0, IF((G8/F8)>('1_Master_Dashboard'!B$2*1.2), "Top Deal 🚀", IF((G8/F8)<'1_Master_Dashboard'!B$2, "Verlust ⚠️", "Standard")), "") | O8: =IF('1_Master_Dashboard'!B$14<0, "MINUS BESTAND ❌", "OK")
A9: 5 | E9: Offen | F9: 0 | G9: 0 | H9: Bar | I9: 0 | J9: Fahrtkosten | K9: =F9*'1_Master_Dashboard'!B$2 | L9: =IF(C9="Verkauf", G9, K9) | M9: =L9-K9-I9 | N9: =IF(F9>0, IF((G9/F9)>('1_Master_Dashboard'!B$2*1.2), "Top Deal 🚀", IF((G9/F9)<'1_Master_Dashboard'!B$2, "Verlust ⚠️", "Standard")), "") | O9: =IF('1_Master_Dashboard'!B$14<0, "MINUS BESTAND ❌", "OK")
A10: 6 | E10: Offen | F10: 0 | G10: 0 | H10: Bar | I10: 0 | J10: Fahrtkosten | K10: =F10*'1_Master_Dashboard'!B$2 | L10: =IF(C10="Verkauf", G10, K10) | M10: =L10-K10-I10 | N10: =IF(F10>0, IF((G10/F10)>('1_Master_Dashboard'!B$2*1.2), "Top Deal 🚀", IF((G10/F10)<'1_Master_Dashboard'!B$2, "Verlust ⚠️", "Standard")), "") | O10: =IF('1_Master_Dashboard'!B$14<0, "MINUS BESTAND ❌", "OK")
A11: 7 | E11: Offen | F11: 0 | G11: 0 | H11: Bar | I11: 0 | J11: Fahrtkosten | K11: =F11*'1_Master_Dashboard'!B$2 | L11: =IF(C11="Verkauf", G11, K11) | M11: =L11-K11-I11 | N11: =IF(F11>0, IF((G11/F11)>('1_Master_Dashboard'!B$2*1.2), "Top Deal 🚀", IF((G11/F11)<'1_Master_Dashboard'!B$2, "Verlust ⚠️", "Standard")), "") | O11: =IF('1_Master_Dashboard'!B$14<0, "MINUS BESTAND ❌", "OK")
A12: 8 | E12: Offen | F12: 0 | G12: 0 | H12: Bar | I12: 0 | J12: Fahrtkosten | K12: =F12*'1_Master_Dashboard'!B$2 | L12: =IF(C12="Verkauf", G12, K12) | M12: =L12-K12-I12 | N12: =IF(F12>0, IF((G12/F12)>('1_Master_Dashboard'!B$2*1.2), "Top Deal 🚀", IF((G12/F12)<'1_Master_Dashboard'!B$2, "Verlust ⚠️", "Standard")), "") | O12: =IF('1_Master_Dashboard'!B$14<0, "MINUS BESTAND ❌", "OK")
A13: 9 | E13: Offen | F13: 0 | G13: 0 | H13: Bar | I13: 0 | J13: Fahrtkosten | K13: =F13*'1_Master_Dashboard'!B$2 | L13: =IF(C13="Verkauf", G13, K13) | M13: =L13-K13-I13 | N13: =IF(F13>0, IF((G13/F13)>('1_Master_Dashboard'!B$2*1.2), "Top Deal 🚀", IF((G13/F13)<'1_Master_Dashboard'!B$2, "Verlust ⚠️", "Standard")), "") | O13: =IF('1_Master_Dashboard'!B$14<0, "MINUS BESTAND ❌", "OK")
A14: 10 | E14: Offen | F14: 0 | G14: 0 | H14: Bar | I14: 0 | J14: Fahrtkosten | K14: =F14*'1_Master_Dashboard'!B$2 | L14: =IF(C14="Verkauf", G14, K14) | M14: =L14-K14-I14 | N14: =IF(F14>0, IF((G14/F14)>('1_Master_Dashboard'!B$2*1.2), "Top Deal 🚀", IF((G14/F14)<'1_Master_Dashboard'!B$2, "Verlust ⚠️", "Standard")), "") | O14: =IF('1_Master_Dashboard'!B$14<0, "MINUS BESTAND ❌", "OK")
A15: 11 | E15: Offen | F15: 0 | G15: 0 | H15: Bar | I15: 0 | J15: Fahrtkosten | K15: =F15*'1_Master_Dashboard'!B$2 | L15: =IF(C15="Verkauf", G15, K15) | M15: =L15-K15-I15 | N15: =IF(F15>0, IF((G15/F15)>('1_Master_Dashboard'!B$2*1.2), "Top Deal 🚀", IF((G15/F15)<'1_Master_Dashboard'!B$2, "Verlust ⚠️", "Standard")), "") | O15: =IF('1_Master_Dashboard'!B$14<0, "MINUS BESTAND ❌", "OK")
A16: 12 | E16: Offen | F16: 0 | G16: 0 | H16: Bar | I16: 0 | J16: Fahrtkosten | K16: =F16*'1_Master_Dashboard'!B$2 | L16: =IF(C16="Verkauf", G16, K16) | M16: =L16-K16-I16 | N16: =IF(F16>0, IF((G16/F16)>('1_Master_Dashboard'!B$2*1.2), "Top Deal 🚀", IF((G16/F16)<'1_Master_Dashboard'!B$2, "Verlust ⚠️", "Standard")), "") | O16: =IF('1_Master_Dashboard'!B$14<0, "MINUS BESTAND ❌", "OK")
... A44: 40 | E44: Offen | F44: 0 | G44: 0 | H44: Bar | I44: 0 | J44: Fahrtkosten | K44: =F44*'1_Master_Dashboard'!B$2 | L44: =IF(C44="Verkauf", G44, K44) | M44: =L44-K44-I44 | N44: =IF(F44>0, IF((G44/F44)>('1_Master_Dashboard'!B$2*1.2), "Top Deal 🚀", IF((G44/F44)<'1_Master_Dashboard'!B$2, "Verlust ⚠️", "Standard")), "") | O44: =IF('1_Master_Dashboard'!B$14<0, "MINUS BESTAND ❌", "OK")

Sheet 3b_Log_Boryana
B1: ⬇️ HIER EINTRAGEN (EINGABEBEREICH) ⬇️ | K1: 🚫 NICHT ÄNDERN (AUTOMATISCHE FORMELN) 🚫
A4: 🔒 Nr | B4: ✏️ Datum | C4: ✏️ Art | D4: ✏️ Kunde / Notiz | E4: ✏️ Zahlung | F4: ✏️ Menge (g) | G4: ✏️ Preis (CHF) | H4: ✏️ Zahlungsart | I4: ✏️ Spesen (CHF) | J4: ✏️ Spesen-Kategorie | K4: 🔒 Basiswert (CHF) | L4: 🔒 Erlös intern (CHF) | M4: 🔒 Netto Profit (CHF) | N4: 🔒 Deal-Rating | O4: 🔒 Lager-Warnung
A5: 1 | E5: Offen | F5: 0 | G5: 0 | H5: Bar | I5: 0 | J5: Fahrtkosten | K5: =F5*'1_Master_Dashboard'!B$2 | L5: =IF(C5="Verkauf", G5, K5) | M5: =L5-K5-I5 | N5: =IF(F5>0, IF((G5/F5)>('1_Master_Dashboard'!B$2*1.2), "Top Deal 🚀", IF((G5/F5)<'1_Master_Dashboard'!B$2, "Verlust ⚠️", "Standard")), "") | O5: =IF('1_Master_Dashboard'!B$14<0, "MINUS BESTAND ❌", "OK")
A6: 2 | E6: Offen | F6: 0 | G6: 0 | H6: Bar | I6: 0 | J6: Fahrtkosten | K6: =F6*'1_Master_Dashboard'!B$2 | L6: =IF(C6="Verkauf", G6, K6) | M6: =L6-K6-I6 | N6: =IF(F6>0, IF((G6/F6)>('1_Master_Dashboard'!B$2*1.2), "Top Deal 🚀", IF((G6/F6)<'1_Master_Dashboard'!B$2, "Verlust ⚠️", "Standard")), "") | O6: =IF('1_Master_Dashboard'!B$14<0, "MINUS BESTAND ❌", "OK")
A7: 3 | E7: Offen | F7: 0 | G7: 0 | H7: Bar | I7: 0 | J7: Fahrtkosten | K7: =F7*'1_Master_Dashboard'!B$2 | L7: =IF(C7="Verkauf", G7, K7) | M7: =L7-K7-I7 | N7: =IF(F7>0, IF((G7/F7)>('1_Master_Dashboard'!B$2*1.2), "Top Deal 🚀", IF((G7/F7)<'1_Master_Dashboard'!B$2, "Verlust ⚠️", "Standard")), "") | O7: =IF('1_Master_Dashboard'!B$14<0, "MINUS BESTAND ❌", "OK")
A8: 4 | E8: Offen | F8: 0 | G8: 0 | H8: Bar | I8: 0 | J8: Fahrtkosten | K8: =F8*'1_Master_Dashboard'!B$2 | L8: =IF(C8="Verkauf", G8, K8) | M8: =L8-K8-I8 | N8: =IF(F8>0, IF((G8/F8)>('1_Master_Dashboard'!B$2*1.2), "Top Deal 🚀", IF((G8/F8)<'1_Master_Dashboard'!B$2, "Verlust ⚠️", "Standard")), "") | O8: =IF('1_Master_Dashboard'!B$14<0, "MINUS BESTAND ❌", "OK")
A9: 5 | E9: Offen | F9: 0 | G9: 0 | H9: Bar | I9: 0 | J9: Fahrtkosten | K9: =F9*'1_Master_Dashboard'!B$2 | L9: =IF(C9="Verkauf", G9, K9) | M9: =L9-K9-I9 | N9: =IF(F9>0, IF((G9/F9)>('1_Master_Dashboard'!B$2*1.2), "Top Deal 🚀", IF((G9/F9)<'1_Master_Dashboard'!B$2, "Verlust ⚠️", "Standard")), "") | O9: =IF('1_Master_Dashboard'!B$14<0, "MINUS BESTAND ❌", "OK")
A10: 6 | E10: Offen | F10: 0 | G10: 0 | H10: Bar | I10: 0 | J10: Fahrtkosten | K10: =F10*'1_Master_Dashboard'!B$2 | L10: =IF(C10="Verkauf", G10, K10) | M10: =L10-K10-I10 | N10: =IF(F10>0, IF((G10/F10)>('1_Master_Dashboard'!B$2*1.2), "Top Deal 🚀", IF((G10/F10)<'1_Master_Dashboard'!B$2, "Verlust ⚠️", "Standard")), "") | O10: =IF('1_Master_Dashboard'!B$14<0, "MINUS BESTAND ❌", "OK")
A11: 7 | E11: Offen | F11: 0 | G11: 0 | H11: Bar | I11: 0 | J11: Fahrtkosten | K11: =F11*'1_Master_Dashboard'!B$2 | L11: =IF(C11="Verkauf", G11, K11) | M11: =L11-K11-I11 | N11: =IF(F11>0, IF((G11/F11)>('1_Master_Dashboard'!B$2*1.2), "Top Deal 🚀", IF((G11/F11)<'1_Master_Dashboard'!B$2, "Verlust ⚠️", "Standard")), "") | O11: =IF('1_Master_Dashboard'!B$14<0, "MINUS BESTAND ❌", "OK")
A12: 8 | E12: Offen | F12: 0 | G12: 0 | H12: Bar | I12: 0 | J12: Fahrtkosten | K12: =F12*'1_Master_Dashboard'!B$2 | L12: =IF(C12="Verkauf", G12, K12) | M12: =L12-K12-I12 | N12: =IF(F12>0, IF((G12/F12)>('1_Master_Dashboard'!B$2*1.2), "Top Deal 🚀", IF((G12/F12)<'1_Master_Dashboard'!B$2, "Verlust ⚠️", "Standard")), "") | O12: =IF('1_Master_Dashboard'!B$14<0, "MINUS BESTAND ❌", "OK")
A13: 9 | E13: Offen | F13: 0 | G13: 0 | H13: Bar | I13: 0 | J13: Fahrtkosten | K13: =F13*'1_Master_Dashboard'!B$2 | L13: =IF(C13="Verkauf", G13, K13) | M13: =L13-K13-I13 | N13: =IF(F13>0, IF((G13/F13)>('1_Master_Dashboard'!B$2*1.2), "Top Deal 🚀", IF((G13/F13)<'1_Master_Dashboard'!B$2, "Verlust ⚠️", "Standard")), "") | O13: =IF('1_Master_Dashboard'!B$14<0, "MINUS BESTAND ❌", "OK")
A14: 10 | E14: Offen | F14: 0 | G14: 0 | H14: Bar | I14: 0 | J14: Fahrtkosten | K14: =F14*'1_Master_Dashboard'!B$2 | L14: =IF(C14="Verkauf", G14, K14) | M14: =L14-K14-I14 | N14: =IF(F14>0, IF((G14/F14)>('1_Master_Dashboard'!B$2*1.2), "Top Deal 🚀", IF((G14/F14)<'1_Master_Dashboard'!B$2, "Verlust ⚠️", "Standard")), "") | O14: =IF('1_Master_Dashboard'!B$14<0, "MINUS BESTAND ❌", "OK")
A15: 11 | E15: Offen | F15: 0 | G15: 0 | H15: Bar | I15: 0 | J15: Fahrtkosten | K15: =F15*'1_Master_Dashboard'!B$2 | L15: =IF(C15="Verkauf", G15, K15) | M15: =L15-K15-I15 | N15: =IF(F15>0, IF((G15/F15)>('1_Master_Dashboard'!B$2*1.2), "Top Deal 🚀", IF((G15/F15)<'1_Master_Dashboard'!B$2, "Verlust ⚠️", "Standard")), "") | O15: =IF('1_Master_Dashboard'!B$14<0, "MINUS BESTAND ❌", "OK")
A16: 12 | E16: Offen | F16: 0 | G16: 0 | H16: Bar | I16: 0 | J16: Fahrtkosten | K16: =F16*'1_Master_Dashboard'!B$2 | L16: =IF(C16="Verkauf", G16, K16) | M16: =L16-K16-I16 | N16: =IF(F16>0, IF((G16/F16)>('1_Master_Dashboard'!B$2*1.2), "Top Deal 🚀", IF((G16/F16)<'1_Master_Dashboard'!B$2, "Verlust ⚠️", "Standard")), "") | O16: =IF('1_Master_Dashboard'!B$14<0, "MINUS BESTAND ❌", "OK")
... A44: 40 | E44: Offen | F44: 0 | G44: 0 | H44: Bar | I44: 0 | J44: Fahrtkosten | K44: =F44*'1_Master_Dashboard'!B$2 | L44: =IF(C44="Verkauf", G44, K44) | M44: =L44-K44-I44 | N44: =IF(F44>0, IF((G44/F44)>('1_Master_Dashboard'!B$2*1.2), "Top Deal 🚀", IF((G44/F44)<'1_Master_Dashboard'!B$2, "Verlust ⚠️", "Standard")), "") | O44: =IF('1_Master_Dashboard'!B$14<0, "MINUS BESTAND ❌", "OK")

Sheet 4_Kunden_CRM
A1: ⬇️ NAMEN HIER REIN ⬇️ | B1: 🚫 NICHT ÄNDERN (FORMELN) 🚫
A2: ✏️ Kunden Name (HIER EINTRAGEN) | B2: 🔒 Total Gekauft (g) | C2: 🔒 Bezahlt (CHF) | D2: 🔒 Offen (Schulden) (CHF) | E2: 🔒 Ø Preis / g (CHF) | F2: 🔒 Level | G2: 🔒 Mahn-Status
A3: Zahnarzt | B3: =SUMIFS('3a_Log_Morris'!F:F, '3a_Log_Morris'!D:D, A3, '3a_Log_Morris'!C:C, "Verkauf") + SUMIFS('3b_Log_Boryana'!F:F, '3b_Log_Boryana'!D:D, A3, '3b_Log_Boryana'!C:C, "Verkauf") | C3: =SUMIFS('3a_Log_Morris'!G:G, '3a_Log_Morris'!D:D, A3, '3a_Log_Morris'!E:E, "Bezahlt") + SUMIFS('3b_Log_Boryana'!G:G, '3b_Log_Boryana'!D:D, A3, '3b_Log_Boryana'!E:E, "Bezahlt") | D3: =SUMIFS('3a_Log_Morris'!G:G, '3a_Log_Morris'!D:D, A3, '3a_Log_Morris'!E:E, "Offen") + SUMIFS('3b_Log_Boryana'!G:G, '3b_Log_Boryana'!D:D, A3, '3b_Log_Boryana'!E:E, "Offen") | E3: =IF(B3>0, (C3+D3)/B3, 0) | F3: =IF(B3>=15, "Whale 🐋", IF(B3>=5, "VIP 👑", "")) | G3: =IF(D3>0, "Zahlung ausstehend ⚠️", "Bezahlt 🟢")
A4: Sandro | B4: =SUMIFS('3a_Log_Morris'!F:F, '3a_Log_Morris'!D:D, A4, '3a_Log_Morris'!C:C, "Verkauf") + SUMIFS('3b_Log_Boryana'!F:F, '3b_Log_Boryana'!D:D, A4, '3b_Log_Boryana'!C:C, "Verkauf") | C4: =SUMIFS('3a_Log_Morris'!G:G, '3a_Log_Morris'!D:D, A4, '3a_Log_Morris'!E:E, "Bezahlt") + SUMIFS('3b_Log_Boryana'!G:G, '3b_Log_Boryana'!D:D, A4, '3b_Log_Boryana'!E:E, "Bezahlt") | D4: =SUMIFS('3a_Log_Morris'!G:G, '3a_Log_Morris'!D:D, A4, '3a_Log_Morris'!E:E, "Offen") + SUMIFS('3b_Log_Boryana'!G:G, '3b_Log_Boryana'!D:D, A4, '3b_Log_Boryana'!E:E, "Offen") | E4: =IF(B4>0, (C4+D4)/B4, 0) | F4: =IF(B4>=15, "Whale 🐋", IF(B4>=5, "VIP 👑", "")) | G4: =IF(D4>0, "Zahlung ausstehend ⚠️", "Bezahlt 🟢")
A5: Martin | B5: =SUMIFS('3a_Log_Morris'!F:F, '3a_Log_Morris'!D:D, A5, '3a_Log_Morris'!C:C, "Verkauf") + SUMIFS('3b_Log_Boryana'!F:F, '3b_Log_Boryana'!D:D, A5, '3b_Log_Boryana'!C:C, "Verkauf") | C5: =SUMIFS('3a_Log_Morris'!G:G, '3a_Log_Morris'!D:D, A5, '3a_Log_Morris'!E:E, "Bezahlt") + SUMIFS('3b_Log_Boryana'!G:G, '3b_Log_Boryana'!D:D, A5, '3b_Log_Boryana'!E:E, "Bezahlt") | D5: =SUMIFS('3a_Log_Morris'!G:G, '3a_Log_Morris'!D:D, A5, '3a_Log_Morris'!E:E, "Offen") + SUMIFS('3b_Log_Boryana'!G:G, '3b_Log_Boryana'!D:D, A5, '3b_Log_Boryana'!E:E, "Offen") | E5: =IF(B5>0, (C5+D5)/B5, 0) | F5: =IF(B5>=15, "Whale 🐋", IF(B5>=5, "VIP 👑", "")) | G5: =IF(D5>0, "Zahlung ausstehend ⚠️", "Bezahlt 🟢")
A6: Ruben | B6: =SUMIFS('3a_Log_Morris'!F:F, '3a_Log_Morris'!D:D, A6, '3a_Log_Morris'!C:C, "Verkauf") + SUMIFS('3b_Log_Boryana'!F:F, '3b_Log_Boryana'!D:D, A6, '3b_Log_Boryana'!C:C, "Verkauf") | C6: =SUMIFS('3a_Log_Morris'!G:G, '3a_Log_Morris'!D:D, A6, '3a_Log_Morris'!E:E, "Bezahlt") + SUMIFS('3b_Log_Boryana'!G:G, '3b_Log_Boryana'!D:D, A6, '3b_Log_Boryana'!E:E, "Bezahlt") | D6: =SUMIFS('3a_Log_Morris'!G:G, '3a_Log_Morris'!D:D, A6, '3a_Log_Morris'!E:E, "Offen") + SUMIFS('3b_Log_Boryana'!G:G, '3b_Log_Boryana'!D:D, A6, '3b_Log_Boryana'!E:E, "Offen") | E6: =IF(B6>0, (C6+D6)/B6, 0) | F6: =IF(B6>=15, "Whale 🐋", IF(B6>=5, "VIP 👑", "")) | G6: =IF(D6>0, "Zahlung ausstehend ⚠️", "Bezahlt 🟢")
A7: Kunde X | B7: =SUMIFS('3a_Log_Morris'!F:F, '3a_Log_Morris'!D:D, A7, '3a_Log_Morris'!C:C, "Verkauf") + SUMIFS('3b_Log_Boryana'!F:F, '3b_Log_Boryana'!D:D, A7, '3b_Log_Boryana'!C:C, "Verkauf") | C7: =SUMIFS('3a_Log_Morris'!G:G, '3a_Log_Morris'!D:D, A7, '3a_Log_Morris'!E:E, "Bezahlt") + SUMIFS('3b_Log_Boryana'!G:G, '3b_Log_Boryana'!D:D, A7, '3b_Log_Boryana'!E:E, "Bezahlt") | D7: =SUMIFS('3a_Log_Morris'!G:G, '3a_Log_Morris'!D:D, A7, '3a_Log_Morris'!E:E, "Offen") + SUMIFS('3b_Log_Boryana'!G:G, '3b_Log_Boryana'!D:D, A7, '3b_Log_Boryana'!E:E, "Offen") | E7: =IF(B7>0, (C7+D7)/B7, 0) | F7: =IF(B7>=15, "Whale 🐋", IF(B7>=5, "VIP 👑", "")) | G7: =IF(D7>0, "Zahlung ausstehend ⚠️", "Bezahlt 🟢")
B8: =SUMIFS('3a_Log_Morris'!F:F, '3a_Log_Morris'!D:D, A8, '3a_Log_Morris'!C:C, "Verkauf") + SUMIFS('3b_Log_Boryana'!F:F, '3b_Log_Boryana'!D:D, A8, '3b_Log_Boryana'!C:C, "Verkauf") | C8: =SUMIFS('3a_Log_Morris'!G:G, '3a_Log_Morris'!D:D, A8, '3a_Log_Morris'!E:E, "Bezahlt") + SUMIFS('3b_Log_Boryana'!G:G, '3b_Log_Boryana'!D:D, A8, '3b_Log_Boryana'!E:E, "Bezahlt") | D8: =SUMIFS('3a_Log_Morris'!G:G, '3a_Log_Morris'!D:D, A8, '3a_Log_Morris'!E:E, "Offen") + SUMIFS('3b_Log_Boryana'!G:G, '3b_Log_Boryana'!D:D, A8, '3b_Log_Boryana'!E:E, "Offen") | E8: =IF(B8>0, (C8+D8)/B8, 0) | F8: =IF(B8>=15, "Whale 🐋", IF(B8>=5, "VIP 👑", "")) | G8: =IF(D8>0, "Zahlung ausstehend ⚠️", "Bezahlt 🟢")
B9: =SUMIFS('3a_Log_Morris'!F:F, '3a_Log_Morris'!D:D, A9, '3a_Log_Morris'!C:C, "Verkauf") + SUMIFS('3b_Log_Boryana'!F:F, '3b_Log_Boryana'!D:D, A9, '3b_Log_Boryana'!C:C, "Verkauf") | C9: =SUMIFS('3a_Log_Morris'!G:G, '3a_Log_Morris'!D:D, A9, '3a_Log_Morris'!E:E, "Bezahlt") + SUMIFS('3b_Log_Boryana'!G:G, '3b_Log_Boryana'!D:D, A9, '3b_Log_Boryana'!E:E, "Bezahlt") | D9: =SUMIFS('3a_Log_Morris'!G:G, '3a_Log_Morris'!D:D, A9, '3a_Log_Morris'!E:E, "Offen") + SUMIFS('3b_Log_Boryana'!G:G, '3b_Log_Boryana'!D:D, A9, '3b_Log_Boryana'!E:E, "Offen") | E9: =IF(B9>0, (C9+D9)/B9, 0) | F9: =IF(B9>=15, "Whale 🐋", IF(B9>=5, "VIP 👑", "")) | G9: =IF(D9>0, "Zahlung ausstehend ⚠️", "Bezahlt 🟢")
B10: =SUMIFS('3a_Log_Morris'!F:F, '3a_Log_Morris'!D:D, A10, '3a_Log_Morris'!C:C, "Verkauf") + SUMIFS('3b_Log_Boryana'!F:F, '3b_Log_Boryana'!D:D, A10, '3b_Log_Boryana'!C:C, "Verkauf") | C10: =SUMIFS('3a_Log_Morris'!G:G, '3a_Log_Morris'!D:D, A10, '3a_Log_Morris'!E:E, "Bezahlt") + SUMIFS('3b_Log_Boryana'!G:G, '3b_Log_Boryana'!D:D, A10, '3b_Log_Boryana'!E:E, "Bezahlt") | D10: =SUMIFS('3a_Log_Morris'!G:G, '3a_Log_Morris'!D:D, A10, '3a_Log_Morris'!E:E, "Offen") + SUMIFS('3b_Log_Boryana'!G:G, '3b_Log_Boryana'!D:D, A10, '3b_Log_Boryana'!E:E, "Offen") | E10: =IF(B10>0, (C10+D10)/B10, 0) | F10: =IF(B10>=15, "Whale 🐋", IF(B10>=5, "VIP 👑", "")) | G10: =IF(D10>0, "Zahlung ausstehend ⚠️", "Bezahlt 🟢")
